fractal_client/__init__.py
fractal_client/authclient.py
fractal_client/client.py
fractal_client/config.py
fractal_client/interface.py
fractal_client/parser.py
fractal_client/response.py
fractal_client/cmd/__init__.py
fractal_client/cmd/_aux_task_caching.py
fractal_client/cmd/_dataset.py
fractal_client/cmd/_group.py
fractal_client/cmd/_job.py
fractal_client/cmd/_profile.py
fractal_client/cmd/_project.py
fractal_client/cmd/_resource.py
fractal_client/cmd/_task.py
fractal_client/cmd/_task_collection.py
fractal_client/cmd/_user.py
fractal_client/cmd/_workflow.py
fractal_client-2.18.2.dist-info/licenses/LICENSE
fractal_client-2.18.2.dist-info/METADATA
fractal_client-2.18.2.dist-info/WHEEL
fractal_client-2.18.2.dist-info/entry_points.txt
fractal_client-2.18.2.dist-info/top_level.txt
fractal_client-2.18.2.dist-info/RECORD
