Metadata-Version: 2.4
Name: fractal-client
Version: 2.18.2
Summary: Command-line client of the Fractal analytics platform
Author-email: Tommaso Comparin <tommaso.comparin@exact-lab.it>, Marco Franzon <marco.franzon@exact-lab.it>, Yuri Chiucconi <yuri.chiucconi@exact-lab.it>, Jacopo Nespolo <jacopo.nespolo@exact-lab.it>
License-Expression: BSD-3-Clause
Project-URL: homepage, https://github.com/fractal-analytics-platform/fractal-client
Project-URL: repository, https://github.com/fractal-analytics-platform/fractal-client
Project-URL: documentation, https://fractal-analytics-platform.github.io/fractal-client
Project-URL: changelog, https://github.com/fractal-analytics-platform/fractal-client/blob/main/CHANGELOG.md
Requires-Python: <3.15,>=3.11
License-File: LICENSE
Requires-Dist: python-dotenv<1.2.0,>=1.1.0
Requires-Dist: httpx<0.29.0,>=0.28.0
Requires-Dist: PyJWT<3.0.0,>=2.8.0
Requires-Dist: packaging<26.0.0,>=25.0.0
Dynamic: license-file
